[
  {
    "success": "成功",
    "data": {
      "list": [
        {
          "coverImg": "img/plist1.jpg",
          "title": "天籁之战第二季 合辑",
          "number":1893281
        },
        {
          "coverImg": "img/plist2.jpg",
          "title": "上海马拉松跑步歌单",
          "number": 1082167
        },
        {
          "coverImg": "img/plist3.jpg",
          "title": "单身狗慎点的40首浪漫情歌",
          "number":655048
        },
        {
          "coverImg": "img/plist4.jpg",
          "title": "有没有那么一首歌，一听见就崩溃了",
          "number":76351380
        },
        {
          "coverImg": "img/plist5.jpg",
          "title": "心已伤 单身十年又何妨",
          "number":2260097
        },
        {
          "coverImg": "img/plist6.jpg",
          "title": "献给宝宝们的经典儿童歌曲",
          "number":21252552
        }
      ]
    }
  },
  {
    "success": "成功",
    "data": {
      "list": [
        {
          "coverImg": "img/plist7.jpg",
          "title": "KTV必唱的经典华语金曲",
          "number":103067772
        },
        {
          "coverImg": "img/plist8.jpg",
          "title": "翻滚吧！基三！",
          "number":104947
        },
        {
          "coverImg": "img/plist9.jpg",
          "title": "民谣，孤独的灵魂在作祟",
          "number":1325
        },
        {
          "coverImg": "img/plist10.jpg",
          "title": "声之形",
          "number":248
        },
        {
          "coverImg": "img/plist11.jpg",
          "title": "英语动物儿歌",
          "number":1844
        },
        {
          "coverImg": "img/plist12.jpg",
          "title": "有一种爱，隐匿在时光深处止于唇齿",
          "number":1389975
        }
      ]
    }
  },
  {
    "success": "成功",
    "data": {
      "list": [
        {
          "coverImg": "img/plist13.jpg",
          "title": "我们熟悉却叫不出的英语歌",
          "number":32494556
        },
        {
          "coverImg": "img/plist14.jpg",
          "title": "一首熟悉的歌，又让我想起了你",
          "number":6267240
        },
        {
          "coverImg": "img/plist15.jpg",
          "title": "心已伤 单身十年又何妨",
          "number":2725246
        },
        {
          "coverImg": "img/plist16.jpg",
          "title": "一人一首成名曲【珍藏版】",
          "number":144448269
        },
        {
          "coverImg": "img/plist17.jpg",
          "title": "伤感网络歌曲热歌精选合辑",
          "number":24359363
        },
        {
          "coverImg": "img/plist18.jpg",
          "title": "那些伤感的网络对唱情歌",
          "number":32411716
        }
      ]
    }
  },
  {
    "success": "成功",
    "data": {
      "list": [
        {
          "coverImg": "img/plist19.jpg",
          "title": "路上听这些华语DJ就是爽",
          "number":12900242
        },
        {
          "coverImg": "img/plist20.jpg",
          "title": "总给人们惊喜的老唱片",
          "number":20563733
        },
        {
          "coverImg": "img/plist21.jpg",
          "title": "最经典的儿歌，没有之一",
          "number":4399996
        },
        {
          "coverImg": "img/plist22.jpg",
          "title": "可爱的小动物",
          "number":12119748
        },
        {
          "coverImg": "img/plist23.jpg",
          "title": "2017年最火电视剧主题曲",
          "number":15343561
        },
        {
          "coverImg": "img/plist24.jpg",
          "title": "DJ广场舞曲，跟我一起嗨起来",
          "number":34568426
        }
      ]
    }
  }
]